jupyter_launcher_shortcuts/__init__.py
jupyter_launcher_shortcuts/_version.py
jupyter_launcher_shortcuts/api.py
jupyter_launcher_shortcuts/etc/nbextension.json
jupyter_launcher_shortcuts/etc/serverextension.json
jupyter_launcher_shortcuts/static/tree.js
jupyter_launcher_shortcuts-4.0.3.data/data/etc/jupyter/jupyter_server_config.d/jupyter_launcher_shortcuts.json
jupyter_launcher_shortcuts-4.0.3.data/data/share/jupyter/labextensions/jupyterlab-launcher-shortcuts/package.json
jupyter_launcher_shortcuts-4.0.3.data/data/share/jupyter/labextensions/jupyterlab-launcher-shortcuts/static/509.adbb2c88aa3cf02c0d9d.js
jupyter_launcher_shortcuts-4.0.3.data/data/share/jupyter/labextensions/jupyterlab-launcher-shortcuts/static/665.9a6d5b7c40de64ae78ad.js
jupyter_launcher_shortcuts-4.0.3.data/data/share/jupyter/labextensions/jupyterlab-launcher-shortcuts/static/remoteEntry.fe223459174cde67e0b4.js
jupyter_launcher_shortcuts-4.0.3.data/data/share/jupyter/labextensions/jupyterlab-launcher-shortcuts/static/style.js
jupyter_launcher_shortcuts-4.0.3.data/data/share/jupyter/labextensions/jupyterlab-launcher-shortcuts/static/third-party-licenses.json
jupyter_launcher_shortcuts-4.0.3.data/data/share/jupyter/labextensions/jupyterlab-launcher-shortcuts/install.json
jupyter_launcher_shortcuts-4.0.3.dist-info/METADATA
jupyter_launcher_shortcuts-4.0.3.dist-info/WHEEL
jupyter_launcher_shortcuts-4.0.3.dist-info/licenses/LICENSE
jupyter_launcher_shortcuts-4.0.3.dist-info/RECORD
