Metadata-Version: 2.3
Name: jupyter-launcher-shortcuts
Version: 4.0.3
Summary: Provide arbitrary shortcuts for apps in JupyterLab
Project-URL: Homepage, https://github.com/2i2c-org/jupyter-launcher-shortcuts
Project-URL: Bug Tracker, https://github.com/2i2c-org/jupyter-launcher-shortcuts/issues
Project-URL: Repository, https://github.com/2i2c-org/jupyter-launcher-shortcuts.git
Author: Yuvi Panda
License: BSD 3-Clause License
License-File: LICENSE
Keywords: jupyter,jupyterlab,jupyterlab-extension
Classifier: Framework :: Jupyter
Classifier: Framework :: Jupyter :: JupyterLab
Classifier: Framework :: Jupyter :: JupyterLab :: 4
Classifier: Framework :: Jupyter :: JupyterLab :: Extensions
Classifier: Framework :: Jupyter :: JupyterLab :: Extensions :: Prebuilt
Classifier: License :: OSI Approved :: BSD License
Classifier: Programming Language :: Python
Classifier: Programming Language :: Python :: 3
Classifier: Programming Language :: Python :: 3.8
Classifier: Programming Language :: Python :: 3.9
Classifier: Programming Language :: Python :: 3.10
Classifier: Programming Language :: Python :: 3.11
Classifier: Programming Language :: Python :: 3.12
Requires-Python: >=3.8
Requires-Dist: jupyter-server
Requires-Dist: jupyterlab<5,>=4
Requires-Dist: tornado
Requires-Dist: traitlets
